sprocket/__init__.py
sprocket/__main__.py
sprocket/sprocket.py
sprocket/cogs/__init__.py
sprocket/cogs/audio.py
sprocket/cogs/base.py
sprocket/cogs/dice.py
sprocket/cogs/quote.py
sprocket/util/__init__.py
sprocket/util/common.py
sprocket/util/loader.py
sprocket_fizzlebang-0.3.0.dist-info/LICENSE
sprocket_fizzlebang-0.3.0.dist-info/METADATA
sprocket_fizzlebang-0.3.0.dist-info/WHEEL
sprocket_fizzlebang-0.3.0.dist-info/entry_points.txt
sprocket_fizzlebang-0.3.0.dist-info/top_level.txt
sprocket_fizzlebang-0.3.0.dist-info/RECORD
