Metadata-Version: 2.1
Name: sprocket-fizzlebang
Version: 0.3.0
Summary: UNKNOWN
Home-page: https://github.com/gnullbyte/sprocket
Author: Chase Franklin
Author-email: gnullbyte@gmail.com
License: UNKNOWN
Platform: UNKNOWN
Classifier: Programming Language :: Python :: 3
Classifier: License :: OSI Approved :: MIT License
Classifier: Operating System :: POSIX :: Linux
Requires-Dist: dicey
Requires-Dist: discord.py
Requires-Dist: python-dotenv
Requires-Dist: pynacl
Requires-Dist: fuzzywuzzy
Requires-Dist: python-levenshtein
